dm_core/__init__.py
dm_core/tracer/__init__.py
dm_core/tracer/apps.py
dm_core/tracer/constants.py
dm_core/tracer/decorator.py
dm_core/tracer/exception.py
dm_core/tracer/middleware.py
dm_core/tracer/models.py
dm_core/tracer/service.py
dm_core/tracer/migrations/0001_initial.py
dm_core/tracer/migrations/__init__.py
dm_core/tracer/migrations_cd/__init__.py
dm_core/tracer/migrations_cd/migration_001_20240216_073000_http_log_creation.py
dm_core/tracer/migrations_cd/migration_002_20240216_074500_message_log_creation.py
dm_core/tracer/tests/__init__.py
dm_core_tracer-1.0.1.dist-info/licenses/LICENSE
dm_core_tracer-1.0.1.dist-info/METADATA
dm_core_tracer-1.0.1.dist-info/WHEEL
dm_core_tracer-1.0.1.dist-info/top_level.txt
dm_core_tracer-1.0.1.dist-info/RECORD
